{
    "base_url": "https://mp.weixin.qq.com",
    "login": {
        "type": "qrcode",
        "checker": "#app > div.main_bd_new > div:nth-child(3) > div.weui-desktop-panel__hd.weui-desktop-global-mod > div > h2"
    },
    "post": {
        "general": {
            "nav": {
                "steps": [
                    ["c", "#app > div.main_bd_new > div:nth-child(3) > div.weui-desktop-panel__bd > div > div:nth-child(2)"],
                    ["s", 1]
                ],
                "checker": "#title"
            },
            "title": "#title",
            "author": "#author",
            "content": "#ueditor_0",
            "medias": {
                "image": {
                    "upload_method": "CLIPBOARD"
                }
            }
        }
    }
}